odoo/addons/purchase_order_line_price_history_discount/README.rst
odoo/addons/purchase_order_line_price_history_discount/__init__.py
odoo/addons/purchase_order_line_price_history_discount/__manifest__.py
odoo/addons/purchase_order_line_price_history_discount/i18n/es.po
odoo/addons/purchase_order_line_price_history_discount/i18n/it.po
odoo/addons/purchase_order_line_price_history_discount/i18n/purchase_order_line_price_history_discount.pot
odoo/addons/purchase_order_line_price_history_discount/readme/CONTRIBUTORS.rst
odoo/addons/purchase_order_line_price_history_discount/readme/DESCRIPTION.rst
odoo/addons/purchase_order_line_price_history_discount/readme/USAGE.rst
odoo/addons/purchase_order_line_price_history_discount/static/description/icon.png
odoo/addons/purchase_order_line_price_history_discount/static/description/index.html
odoo/addons/purchase_order_line_price_history_discount/tests/__init__.py
odoo/addons/purchase_order_line_price_history_discount/tests/test_purchase_order_line_price_history_discount.py
odoo/addons/purchase_order_line_price_history_discount/wizards/__init__.py
odoo/addons/purchase_order_line_price_history_discount/wizards/purchase_order_line_price_history.py
odoo/addons/purchase_order_line_price_history_discount/wizards/purchase_order_line_price_history.xml
odoo14_addon_purchase_order_line_price_history_discount-14.0.1.0.1.dev7.dist-info/METADATA
odoo14_addon_purchase_order_line_price_history_discount-14.0.1.0.1.dev7.dist-info/WHEEL
odoo14_addon_purchase_order_line_price_history_discount-14.0.1.0.1.dev7.dist-info/top_level.txt
odoo14_addon_purchase_order_line_price_history_discount-14.0.1.0.1.dev7.dist-info/RECORD
